Serv-0.3.0.dist-info/DESCRIPTION.rst
Serv-0.3.0.dist-info/LICENSE.txt
Serv-0.3.0.dist-info/METADATA
Serv-0.3.0.dist-info/RECORD
Serv-0.3.0.dist-info/WHEEL
Serv-0.3.0.dist-info/entry_points.txt
Serv-0.3.0.dist-info/metadata.json
Serv-0.3.0.dist-info/top_level.txt
serv/__init__.py
serv/constants.py
serv/exceptions.py
serv/serv.py
serv/utils.py
serv/init/__init__.py
serv/init/base.py
serv/init/nssm.py
serv/init/systemd.py
serv/init/sysv.py
serv/init/upstart.py
serv/init/binaries/nssm32.exe
serv/init/binaries/nssm64.exe
serv/init/templates/nssm.bat
serv/init/templates/systemd
serv/init/templates/systemd.service
serv/init/templates/sysv
serv/init/templates/sysv.defaults
serv/init/templates/upstart.conf
tests/__init__.py
tests/mock_system.py
tests/test_deploy.py
tests/test_serv.py
