Metadata-Version: 2.0
Name: Serv
Version: 0.3.0
Summary: Init system abstraction API and CLI
Home-page: https://github.com/nir0s/serv
Author: nir0s
Author-email: nir36g@gmail.com
License: LICENSE
Platform: All
Classifier: Programming Language :: Python
Classifier: Programming Language :: Python :: 2.6
Classifier: Programming Language :: Python :: 2.7
Classifier: Programming Language :: Python :: 3.4
Classifier: Programming Language :: Python :: 3.5
Classifier: Natural Language :: English
Classifier: Environment :: Console
Classifier: Intended Audience :: Developers
Classifier: Intended Audience :: Information Technology
Classifier: Intended Audience :: System Administrators
Classifier: License :: OSI Approved :: Apache Software License
Classifier: Operating System :: POSIX :: Linux
Classifier: Operating System :: Microsoft
Classifier: Topic :: Software Development :: Libraries :: Python Modules
Requires-Dist: click (==6.6)
Requires-Dist: jinja2 (==2.8)
Requires-Dist: sh (==1.11)
Requires-Dist: distro (==1.0.1)
